kauldron/__init__.py
kauldron/kd.py
kauldron/kxm.py
kauldron/main.py
kauldron/checkpoints/__init__.py
kauldron/checkpoints/checkpoint_items.py
kauldron/checkpoints/checkpointer.py
kauldron/checkpoints/lazy_checkpoint_manager.py
kauldron/checkpoints/partial_loader.py
kauldron/contrib/README.md
kauldron/contrib/__init__.py
kauldron/contrib/_lazy_imports.py
kauldron/contrib/checkpoints/__init__.py
kauldron/contrib/checkpoints/partial_loader.py
kauldron/contrib/data/__init__.py
kauldron/contrib/data/array_record.py
kauldron/contrib/data/extra_image_ops.py
kauldron/contrib/data/frame_sampling.py
kauldron/contrib/data/pose_preprocessing.py
kauldron/contrib/data/preprocessing.py
kauldron/contrib/data/scenic_ops.py
kauldron/contrib/data/iterators/__init__.py
kauldron/contrib/data/iterators/tfgrain_handler.py
kauldron/contrib/data/py/__init__.py
kauldron/contrib/data/py/preprocessing.py
kauldron/contrib/evals/__init__.py
kauldron/contrib/evals/train_eval.py
kauldron/contrib/losses/__init__.py
kauldron/contrib/losses/point.py
kauldron/contrib/losses/segmentation.py
kauldron/contrib/metrics/__init__.py
kauldron/contrib/metrics/classification.py
kauldron/contrib/metrics/colormaps.py
kauldron/contrib/metrics/depth_estimation.py
kauldron/contrib/metrics/fid.py
kauldron/contrib/metrics/image.py
kauldron/contrib/metrics/multilabel_average_precision.py
kauldron/contrib/metrics/point_tracking.py
kauldron/contrib/metrics/point_tracking_3d.py
kauldron/contrib/metrics/pose.py
kauldron/contrib/metrics/regression.py
kauldron/contrib/metrics/segmentation_tracking.py
kauldron/contrib/metrics/similarity.py
kauldron/contrib/modules/__init__.py
kauldron/contrib/modules/from_xid.py
kauldron/contrib/modules/readout.py
kauldron/contrib/summaries/__init__.py
kauldron/contrib/summaries/image_grid.py
kauldron/contrib/summaries/print_summary.py
kauldron/contrib/train/__init__.py
kauldron/contrib/train/mlflow_metric_writer.py
kauldron/contrib/train/multi_train_step.py
kauldron/data/__init__.py
kauldron-1.3.0.dist-info/licenses/LICENSE
kauldron-1.3.0.dist-info/WHEEL
kauldron-1.3.0.dist-info/METADATA
kauldron-1.3.0.dist-info/RECORD
